clasherjk/client.py
clasherjk/config.py
clasherjk/exceptions.py
clasherjk/models.py
clasherjk-1.0.5.dist-info/licenses/LICENSE
clasherjk-1.0.5.dist-info/METADATA
clasherjk-1.0.5.dist-info/WHEEL
clasherjk-1.0.5.dist-info/top_level.txt
clasherjk-1.0.5.dist-info/RECORD
