Metadata-Version: 2.4
Name: clasherjk
Version: 1.0.5
Summary: A simple and efficient Python wrapper for the official Clash of Clans API, enabling developers to fetch player, clan, and war data with ease.
Author-email: ClasherJK <jkminidev@gmail.com>
License-Expression: MIT
Project-URL: Homepage, https://jktripuri.site
Keywords: clash-of-clans,clasherjk
Classifier: Development Status :: 5 - Production/Stable
Classifier: Intended Audience :: Developers
Classifier: Topic :: Games/Entertainment
Classifier: Programming Language :: Python :: 3
Classifier: Programming Language :: Python :: 3.7
Classifier: Programming Language :: Python :: 3.8
Classifier: Programming Language :: Python :: 3.9
Classifier: Programming Language :: Python :: 3.10
Classifier: Programming Language :: Python :: 3.11
Classifier: Programming Language :: Python :: 3.12
Classifier: Operating System :: OS Independent
Requires-Python: >=3.7
License-File: LICENSE
Requires-Dist: httpx>=0.24.0
Dynamic: license-file
